adede/__init__.py
adede/apps.py
adede/static/adede/css/adede.css
adede/static/adede/js/adede.js
adede/templatetags/__init__.py
adede/templatetags/adede_tags.py
adede-4.1.0.dist-info/AUTHORS.txt
adede-4.1.0.dist-info/LICENSE.txt
adede-4.1.0.dist-info/METADATA
adede-4.1.0.dist-info/WHEEL
adede-4.1.0.dist-info/top_level.txt
adede-4.1.0.dist-info/RECORD
